lemmy_nhl/config.py
lemmy_nhl/draft_bot.py
lemmy_nhl/lemmy_nhl_bot_daemon.py
lemmy_nhl/post_body.py
lemmy_nhl-1.5.11.dist-info/LICENSE
lemmy_nhl-1.5.11.dist-info/METADATA
lemmy_nhl-1.5.11.dist-info/WHEEL
lemmy_nhl-1.5.11.dist-info/entry_points.txt
lemmy_nhl-1.5.11.dist-info/top_level.txt
lemmy_nhl-1.5.11.dist-info/RECORD
