Metadata-Version: 2.1
Name: lemmy-nhl
Version: 1.5.11
Summary: bot to add live scores to lemmy community for hockey games
Home-page: https://github.com/socphoenix/lemmy_nhl_bot
Author: socphoenix
License: Apache 2.0
Keywords: lemmy,hockey,bot
License-File: LICENSE
Requires-Dist: plemmy >=0.3.0
Requires-Dist: requests
